userdb/__init__.py
userdb/auth.py
userdb/config.py
userdb/db.py
userdb/models.py
userdb/schemas.py
userdb/userdb_utils.py
beanone_userdb-0.8.2.dist-info/METADATA
beanone_userdb-0.8.2.dist-info/WHEEL
beanone_userdb-0.8.2.dist-info/licenses/LICENSE
beanone_userdb-0.8.2.dist-info/RECORD
